velour/__init__.py
velour/client.py
velour/coretypes.py
velour/data_generation.py
velour/enums.py
velour/exceptions.py
velour/metatypes.py
velour/typing.py
velour/viz.py
velour/schemas/__init__.py
velour/schemas/constraints.py
velour/schemas/evaluation.py
velour/schemas/filters.py
velour/schemas/geometry.py
velour/schemas/metadata.py
velour/schemas/properties.py
velour_client-0.15.0.dist-info/LICENSE
velour_client-0.15.0.dist-info/METADATA
velour_client-0.15.0.dist-info/WHEEL
velour_client-0.15.0.dist-info/top_level.txt
velour_client-0.15.0.dist-info/RECORD
