Metadata-Version: 2.1
Name: velour-client
Version: 0.15.0
Summary: Python client for the Velour evaluation store
License: MIT License
Project-URL: homepage, https://www.striveworks.com
Requires-Python: >=3.7
License-File: LICENSE
Requires-Dist: requests
Requires-Dist: Pillow >=9.1.0
Requires-Dist: numpy
Requires-Dist: tqdm
Requires-Dist: importlib-metadata ; python_version < "3.8"
Provides-Extra: test
Requires-Dist: pytest ; extra == 'test'
Requires-Dist: coverage ; extra == 'test'
